cmem_plugin_sparql_anything/__init__.py
cmem_plugin_sparql_anything/constants.py
cmem_plugin_sparql_anything/logo.svg
cmem_plugin_sparql_anything/sparql_anything_workflow.py
cmem_plugin_sparql_anything/utils.py
cmem_plugin_sparql_anything-0.5.0.dist-info/LICENSE
cmem_plugin_sparql_anything-0.5.0.dist-info/METADATA
cmem_plugin_sparql_anything-0.5.0.dist-info/WHEEL
cmem_plugin_sparql_anything-0.5.0.dist-info/RECORD
