Metadata-Version: 2.1
Name: cmem-plugin-sparql-anything
Version: 0.5.0
Summary: Query anything with SPARQL to construct Knowledge Graphs.
Home-page: https://github.com/eccenca/cmem-plugin-sparql-anything
License: Apache-2.0
Keywords: eccenca Corporate Memory,plugin
Author: eccenca GmbH
Author-email: cmempy-developer@eccenca.com
Requires-Python: >=3.11,<4.0
Classifier: Development Status :: 4 - Beta
Classifier: Environment :: Plugins
Classifier: License :: OSI Approved :: Apache Software License
Classifier: Programming Language :: Python :: 3
Classifier: Programming Language :: Python :: 3.11
Classifier: Programming Language :: Python :: 3.12
Classifier: Programming Language :: Python :: 3.13
Requires-Dist: cmem-plugin-base (>=4.7.0,<5.0.0)
